mcp_server_demo_lei/__init__.py
mcp_server_demo_lei/main.py
mcp_server_demo_lei-0.1.1.dist-info/METADATA
mcp_server_demo_lei-0.1.1.dist-info/WHEEL
mcp_server_demo_lei-0.1.1.dist-info/entry_points.txt
mcp_server_demo_lei-0.1.1.dist-info/RECORD
