Metadata-Version: 2.4
Name: mcp-server-demo-lei
Version: 0.1.1
Summary: Add your description here
Author-email: chasespace <random2035@qq.com>
Requires-Python: >=3.13
Requires-Dist: httpx>=0.28.1
Requires-Dist: mcp>=1.9.3
